rddl_client/application/attest.py
rddl_client/application/energy.py
rddl_client/application/machine_context.py
rddl_client/application/seed.py
rddl_client/application/transfer.py
rddl_client/config.py
rddl_client/main.py
rddl_client/utils/device_info.py
rddl_client-0.2.0.dist-info/LICENSE
rddl_client-0.2.0.dist-info/METADATA
rddl_client-0.2.0.dist-info/WHEEL
rddl_client-0.2.0.dist-info/entry_points.txt
rddl_client-0.2.0.dist-info/RECORD
