Metadata-Version: 2.1
Name: rddl-client
Version: 0.2.0
Summary: 
License: AGPLv3
Author: Jürgen Eckel
Author-email: juergen@riddleandcode.com
Requires-Python: >=3.10,<4.0
Classifier: License :: Other/Proprietary License
Classifier: Programming Language :: Python :: 3
Classifier: Programming Language :: Python :: 3.10
Classifier: Programming Language :: Python :: 3.11
Requires-Dist: mypy (>=0.982,<0.983)
Requires-Dist: py-dmidecode (>=0.1.0,<0.2.0)
Requires-Dist: python-decouple (>=3.6,<4.0)
Requires-Dist: requests (>=2.28.1,<3.0.0)
Requires-Dist: rich (>=12.6.0,<13.0.0)
Requires-Dist: shellingham (>=1.5.0,<2.0.0)
Requires-Dist: typer (>=0.6.1,<0.7.0)
Requires-Dist: urllib3 (>=1.26.12,<2.0.0)
